cfmaker/__init__.py
cfmaker/fconfig.py
cfmaker/file_manager.py
cfmaker/icompiler.py
cfmaker/tools.py
cfmaker-0.2.0.dist-info/METADATA
cfmaker-0.2.0.dist-info/WHEEL
cfmaker-0.2.0.dist-info/top_level.txt
cfmaker-0.2.0.dist-info/RECORD
