Metadata-Version: 2.1
Name: cfmaker
Version: 0.2.0
Summary: A lightweight compilation tool for Fortran and C projects, primarily targeting the Intel oneAPI compilers, ifort and ifx.
Author-email: littlestar <littlestar002@gmail.com>
Project-URL: Homepage, https://github.com/Littlestar007/fmaker
Project-URL: Issues, https://github.com/Littlestar007/fmaker/issues
Keywords: oneapi,fortran,project,c,compiler
Classifier: Programming Language :: Python :: 3
Classifier: License :: OSI Approved :: MIT License
Classifier: Operating System :: OS Independent
Requires-Python: >=3.8
